erede/Additional.py
erede/Address.py
erede/Authorization.py
erede/Brand.py
erede/Capture.py
erede/Cart.py
erede/Consumer.py
erede/Document.py
erede/Environment.py
erede/Flight.py
erede/Iata.py
erede/Item.py
erede/Passenger.py
erede/Phone.py
erede/RedeError.py
erede/RedeSerializable.py
erede/Refund.py
erede/Store.py
erede/SubMerchant.py
erede/ThreeDSecure.py
erede/Transaction.py
erede/Url.py
erede/__init__.py
erede/eRede.py
erede/service/CancelTransactionService.py
erede/service/CaptureTransactionService.py
erede/service/CreateTransactionService.py
erede/service/GetTransactionService.py
erede/service/TransactionService.py
erede/service/__init__.py
erede_payments-1.0.1.dist-info/LICENSE
erede_payments-1.0.1.dist-info/METADATA
erede_payments-1.0.1.dist-info/WHEEL
erede_payments-1.0.1.dist-info/top_level.txt
erede_payments-1.0.1.dist-info/RECORD
