Metadata-Version: 2.1
Name: erede-payments
Version: 1.0.1
Summary: A package to handle rede payments api
Home-page: https://github.com/nugluke/erede-python
Author: Lucas Rodrigues
Author-email: lucasvemerick@gmail.com
License: UNKNOWN
Platform: UNKNOWN
Classifier: Programming Language :: Python :: 3
Classifier: License :: OSI Approved :: MIT License
Classifier: Operating System :: OS Independent
License-File: LICENSE
Requires-Dist: requests
